channels_multiprocessing.py
channels_multiprocessing-0.1.2.dist-info/METADATA
channels_multiprocessing-0.1.2.dist-info/WHEEL
channels_multiprocessing-0.1.2.dist-info/RECORD
