Metadata-Version: 2.1
Name: channels-multiprocessing
Version: 0.1.2
Summary: Django channels with plain multiprocessing
Home-page: https://github.com/devkral/channels-multiprocessing
License: BSD
Author: Alexander Kaftan
Requires-Python: >=3.9,<4
Classifier: Development Status :: 3 - Alpha
Classifier: Framework :: Django
Classifier: License :: OSI Approved :: BSD License
Classifier: License :: Other/Proprietary License
Classifier: Programming Language :: Python :: 3
Classifier: Programming Language :: Python :: 3.9
Classifier: Programming Language :: Python :: 3.10
Classifier: Programming Language :: Python :: 3.11
Provides-Extra: test
Requires-Dist: async_timeout ; extra == "test"
Requires-Dist: channels
Requires-Dist: pytest ; extra == "test"
Requires-Dist: pytest-asyncio ; extra == "test"
Project-URL: Repository, https://github.com/devkral/channels-multiprocessing
